sglang_router_rs.cpython-312-x86_64-linux-gnu.so
sglang_router/__init__.py
sglang_router/router.py
sglang_rust_test.libs/libcom_err-2abe824b.so.2.1
sglang_rust_test.libs/libgssapi_krb5-497db0c6.so.2.2
sglang_rust_test.libs/libssl-cd1d6220.so.1.0.2k
sglang_rust_test.libs/libpcre-9513aab5.so.1.2.0
sglang_rust_test.libs/libkrb5support-d0bcff84.so.0.1
sglang_rust_test.libs/libkeyutils-dfe70bd6.so.1.5
sglang_rust_test.libs/libcrypto-d3570994.so.1.0.2k
sglang_rust_test.libs/libselinux-0922c95c.so.1
sglang_rust_test.libs/libk5crypto-b1f99d5c.so.3.1
sglang_rust_test.libs/libkrb5-fcafa220.so.3.3
sglang_rust_test-0.1.12.dist-info/top_level.txt
sglang_rust_test-0.1.12.dist-info/RECORD
sglang_rust_test-0.1.12.dist-info/METADATA
sglang_rust_test-0.1.12.dist-info/WHEEL
