Metadata-Version: 2.1
Name: sglang-rust-test
Version: 0.1.12
Summary: A Python wrapper around Rust HelloWorld
Author-email: Your Name <your.email@example.com>
License: MIT
Classifier: Programming Language :: Python :: Implementation :: CPython
Classifier: Programming Language :: Rust
Classifier: Programming Language :: Python :: 3
Requires-Python: >=3.8
